pywe_utils/__init__.py
pywe_utils/utils.py
pywe_utils-1.0.2.dist-info/DESCRIPTION.rst
pywe_utils-1.0.2.dist-info/METADATA
pywe_utils-1.0.2.dist-info/RECORD
pywe_utils-1.0.2.dist-info/WHEEL
pywe_utils-1.0.2.dist-info/metadata.json
pywe_utils-1.0.2.dist-info/top_level.txt
